Metadata-Version: 2.1
Name: pydrugsdatabase
Version: 0.1.0
Summary: Downloads the FDA drugs database along with the NDC codes active ingredients and drug classes
Home-page: https://gitlab.com/marcnealer/pydrugsdatabase
Author: Marc Nealer
Author-email: marcnealer@gmail.com
Classifier: Development Status :: 4 - Beta
Classifier: Intended Audience :: Developers
Classifier: License :: OSI Approved :: MIT License
Classifier: Programming Language :: Python :: 3.11
Requires-Dist: pydantic
Requires-Dist: tinydb
Requires-Dist: requests
